python_package_size/main.py
python_package_size-1.0.1.dist-info/METADATA
python_package_size-1.0.1.dist-info/WHEEL
python_package_size-1.0.1.dist-info/entry_points.txt
python_package_size-1.0.1.dist-info/licenses/LICENSE
python_package_size-1.0.1.dist-info/RECORD
