Metadata-Version: 2.1
Name: python-package-size
Version: 1.0.1
Summary: Learn after-install weight of any Python package including its dependencies.
Project-URL: Homepage, http://github.com/qertoip/python-package-size
Author-email: Piotr Włodarek <contact@qertoip.com>
License: MIT License
License-File: LICENSE
Classifier: Development Status :: 5 - Production/Stable
Classifier: Intended Audience :: Developers
Classifier: Intended Audience :: Science/Research
Classifier: License :: OSI Approved :: MIT License
Requires-Python: >=3.8
Provides-Extra: dev
Requires-Dist: twine; extra == 'dev'
